rmt_utilities/__init__.py
rmt_utilities/_version.py
rmt_utilities/atomicunits.py
rmt_utilities/cross_sec.py
rmt_utilities/data_recon.py
rmt_utilities/dataobjects.py
rmt_utilities/dipole_cli.py
rmt_utilities/gen_hhg.py
rmt_utilities/gen_tas.py
rmt_utilities/plot_dist.py
rmt_utilities/reform_cli.py
rmt_utilities/regress.py
rmt_utilities/rmt_compare.py
rmt_utilities/rmtutil.py
rmt_utilities-1.0.dist-info/AUTHORS.rst
rmt_utilities-1.0.dist-info/LICENSE
rmt_utilities-1.0.dist-info/METADATA
rmt_utilities-1.0.dist-info/WHEEL
rmt_utilities-1.0.dist-info/entry_points.txt
rmt_utilities-1.0.dist-info/top_level.txt
rmt_utilities-1.0.dist-info/RECORD
