Metadata-Version: 2.1
Name: rmt-utilities
Version: 1.0
Summary: Python package for interacting with the high performance,                 parallel fortran code R-matrix with Time
Home-page: https://gitlab.com/abrown41/rmt-utilities
Author: Andrew Brown
Author-email: andrew.brown@qub.ac.uk
License: BSD (3-clause)
Platform: UNKNOWN
Classifier: Development Status :: 2 - Pre-Alpha
Classifier: Natural Language :: English
Classifier: Programming Language :: Python :: 3
Requires-Python: >=3.8
License-File: LICENSE
License-File: AUTHORS.rst
Requires-Dist: pandas
Requires-Dist: numpy
Requires-Dist: matplotlib
Requires-Dist: pathlib
Requires-Dist: f90nml
Requires-Dist: pyyaml
Requires-Dist: pytest
